hshield/__init__.py
hshield/address_shield.py
hshield/document_shield.py
hshield/main.py
hshield/name_shield.py
hshield/requirements.txt
hshield/tests/doc1.txt
hshield-4.0.dist-info/entry_points.txt
hshield-4.0.dist-info/LICENSE
hshield-4.0.dist-info/WHEEL
hshield-4.0.dist-info/METADATA
hshield-4.0.dist-info/RECORD
